cptest/__init__.py
cptest/graph.py
cptest-0.0.1.dist-info/LICENSE
cptest-0.0.1.dist-info/METADATA
cptest-0.0.1.dist-info/WHEEL
cptest-0.0.1.dist-info/top_level.txt
cptest-0.0.1.dist-info/RECORD
