Metadata-Version: 2.1
Name: cptest
Version: 0.0.1
Summary: Library with objects for writing generators and validators for competitive programming questions.
Home-page: https://github.com/pypa/sampleproject
Author: Jackmin
Author-email: wid190507@siswa.um.edu.my
License: UNKNOWN
Project-URL: Bug Tracker, https://github.com/pypa/sampleproject/issues
Platform: UNKNOWN
Classifier: Programming Language :: Python :: 3
Classifier: License :: OSI Approved :: MIT License
Classifier: Operating System :: OS Independent
Requires-Python: >=3.6
License-File: LICENSE
